[
  {
    "pidx": "4463",
    "jhno": "103",
    "pno": "1",
    "url": "https://japan-heritage.bunka.go.jp/ja/culturalproperties/result/5424/",
    "status": "-",
    "name": "長崎街道",
    "yomi": "",
    "spot": "福岡県北九州市福岡県飯塚市佐賀県佐賀市佐賀県小城市佐賀県嬉野市長崎県長崎市長崎県諫早市長崎県大村市",
    "lat": "33.254738400000015",
    "lng": "130.30293",
    "zoom": "17",
    "image": "https://japan-heritage.bunka.go.jp/ja/datas/cache/images/2022/08/15/500x343_2ae395417f98b42be3d881be00011165_7ea4bec431019865a944d1fde40625dfc399d0cb.jpeg"
  },
  {
    "pidx": "4464",
    "jhno": "103",
    "pno": "2",
    "url": "https://japan-heritage.bunka.go.jp/ja/culturalproperties/result/5425/",
    "status": "国指定史跡",
    "name": "出島和蘭商館跡",
    "yomi": "",
    "spot": "長崎県長崎市",
    "lat": "32.743371000000046",
    "lng": "129.8740969",
    "zoom": "15",
    "image": "https://japan-heritage.bunka.go.jp/ja/datas/cache/images/2022/08/15/500x343_2ae395417f98b42be3d881be00011165_bdd468cd31ca9d6c3911af9e35a8f996c3d328c5.jpeg"
  },
  {
    "pidx": "4465",
    "jhno": "103",
    "pno": "3",
    "url": "https://japan-heritage.bunka.go.jp/ja/culturalproperties/result/5426/",
    "status": "国指定重要無形民俗文化財",
    "name": "長崎くんちの奉納踊",
    "yomi": "",
    "spot": "長崎県長崎市",
    "lat": "",
    "lng": "",
    "zoom": "",
    "image": ""
  },
  {
    "pidx": "4466",
    "jhno": "103",
    "pno": "4",
    "url": "https://japan-heritage.bunka.go.jp/ja/culturalproperties/result/5427/",
    "status": "国指定重要文化財、県指定有形文化財　他",
    "name": "興福寺",
    "yomi": "",
    "spot": "長崎県長崎市",
    "lat": "32.747875400000034",
    "lng": "129.883901",
    "zoom": "15",
    "image": "https://japan-heritage.bunka.go.jp/ja/datas/cache/images/2022/08/15/500x343_2ae395417f98b42be3d881be00011165_0973918512ea6f046245aa8d30ba15025469d40c.jpeg"
  },
  {
    "pidx": "4467",
    "jhno": "103",
    "pno": "5",
    "url": "https://japan-heritage.bunka.go.jp/ja/culturalproperties/result/5428/",
    "status": "国宝、国指定重要文化財他",
    "name": "崇福寺",
    "yomi": "",
    "spot": "長崎県長崎市",
    "lat": "32.74242700000003",
    "lng": "129.88350120000004",
    "zoom": "15",
    "image": "https://japan-heritage.bunka.go.jp/ja/datas/cache/images/2022/08/15/500x343_2ae395417f98b42be3d881be00011165_a2d8158d0db9e0b65249adba7ad824efa99798ac.jpeg"
  },
  {
    "pidx": "4468",
    "jhno": "103",
    "pno": "6",
    "url": "https://japan-heritage.bunka.go.jp/ja/culturalproperties/result/5429/",
    "status": "市指定史跡",
    "name": "旧唐人屋敷内土神堂・観音堂・天后堂",
    "yomi": "",
    "spot": "長崎県長崎市",
    "lat": "32.73924489999999",
    "lng": "129.876556",
    "zoom": "15",
    "image": "https://japan-heritage.bunka.go.jp/ja/datas/cache/images/2022/08/15/500x343_2ae395417f98b42be3d881be00011165_e2dfffa6ff59cbda68f7b13c2dea058ebde201b0.jpeg"
  },
  {
    "pidx": "4469",
    "jhno": "103",
    "pno": "7",
    "url": "https://japan-heritage.bunka.go.jp/ja/culturalproperties/result/5430/",
    "status": "国指定重要文化財、県指定有形文化財　他",
    "name": "聖福寺",
    "yomi": "",
    "spot": "長崎県長崎市",
    "lat": "32.7529991",
    "lng": "129.876936",
    "zoom": "15",
    "image": "https://japan-heritage.bunka.go.jp/ja/datas/cache/images/2022/08/15/500x343_2ae395417f98b42be3d881be00011165_6978bdb559b158402998152583732640be0d6bca.jpeg"
  },
  {
    "pidx": "4470",
    "jhno": "103",
    "pno": "8",
    "url": "https://japan-heritage.bunka.go.jp/ja/culturalproperties/result/5431/",
    "status": "国認定旧重要美術品",
    "name": "紙本著色唐蘭館の図",
    "yomi": "",
    "spot": "長崎県長崎市",
    "lat": "32.75290730000003",
    "lng": "129.87948780000002",
    "zoom": "15",
    "image": "https://japan-heritage.bunka.go.jp/ja/datas/cache/images/2022/08/15/500x343_2ae395417f98b42be3d881be00011165_8931f0372f82e9661d11b2bda6aca1362193c76e.jpeg"
  },
  {
    "pidx": "4471",
    "jhno": "103",
    "pno": "9",
    "url": "https://japan-heritage.bunka.go.jp/ja/culturalproperties/result/5432/",
    "status": "県指定有形文化財",
    "name": "職人尽(菓子製造の図)",
    "yomi": "",
    "spot": "長崎県長崎市",
    "lat": "32.75497890000002",
    "lng": "129.88424010000003",
    "zoom": "15",
    "image": "https://japan-heritage.bunka.go.jp/ja/datas/cache/images/2022/08/15/500x343_2ae395417f98b42be3d881be00011165_90957c625c2fd770914b4d6aa77af4a027e266d3.jpeg"
  },
  {
    "pidx": "4472",
    "jhno": "103",
    "pno": "10",
    "url": "https://japan-heritage.bunka.go.jp/ja/culturalproperties/result/5433/",
    "status": "未指定(民俗技術)",
    "name": "カステラ",
    "yomi": "",
    "spot": "長崎県長崎市",
    "lat": "",
    "lng": "",
    "zoom": "",
    "image": ""
  },
  {
    "pidx": "4473",
    "jhno": "103",
    "pno": "11",
    "url": "https://japan-heritage.bunka.go.jp/ja/culturalproperties/result/5434/",
    "status": "未指定(民俗技術)",
    "name": "有平糖",
    "yomi": "",
    "spot": "長崎県長崎市",
    "lat": "",
    "lng": "",
    "zoom": "",
    "image": ""
  },
  {
    "pidx": "4474",
    "jhno": "103",
    "pno": "12",
    "url": "https://japan-heritage.bunka.go.jp/ja/culturalproperties/result/5435/",
    "status": "未指定(民俗技術)",
    "name": "ぬくめ細工",
    "yomi": "",
    "spot": "長崎県長崎市",
    "lat": "",
    "lng": "",
    "zoom": "",
    "image": ""
  },
  {
    "pidx": "4475",
    "jhno": "103",
    "pno": "13",
    "url": "https://japan-heritage.bunka.go.jp/ja/culturalproperties/result/5436/",
    "status": "未指定(民俗技術)",
    "name": "ザボン漬",
    "yomi": "",
    "spot": "長崎県長崎市",
    "lat": "",
    "lng": "",
    "zoom": "",
    "image": ""
  },
  {
    "pidx": "4476",
    "jhno": "103",
    "pno": "14",
    "url": "https://japan-heritage.bunka.go.jp/ja/culturalproperties/result/5437/",
    "status": "未指定(民俗技術)",
    "name": "一口香",
    "yomi": "",
    "spot": "長崎県長崎市",
    "lat": "",
    "lng": "",
    "zoom": "",
    "image": ""
  },
  {
    "pidx": "4477",
    "jhno": "103",
    "pno": "15",
    "url": "https://japan-heritage.bunka.go.jp/ja/culturalproperties/result/5438/",
    "status": "未指定(民俗技術)",
    "name": "寒菊",
    "yomi": "",
    "spot": "長崎県長崎市",
    "lat": "",
    "lng": "",
    "zoom": "",
    "image": ""
  },
  {
    "pidx": "4478",
    "jhno": "103",
    "pno": "16",
    "url": "https://japan-heritage.bunka.go.jp/ja/culturalproperties/result/5439/",
    "status": "未指定(民俗技術)",
    "name": "口砂香",
    "yomi": "",
    "spot": "長崎県長崎市",
    "lat": "",
    "lng": "",
    "zoom": "",
    "image": ""
  },
  {
    "pidx": "4479",
    "jhno": "103",
    "pno": "17",
    "url": "https://japan-heritage.bunka.go.jp/ja/culturalproperties/result/5440/",
    "status": "未指定（器具）",
    "name": "引釜",
    "yomi": "",
    "spot": "長崎県長崎市",
    "lat": "",
    "lng": "",
    "zoom": "",
    "image": ""
  },
  {
    "pidx": "4480",
    "jhno": "103",
    "pno": "18",
    "url": "https://japan-heritage.bunka.go.jp/ja/culturalproperties/result/5441/",
    "status": "市指定史跡",
    "name": "大村街道",
    "yomi": "",
    "spot": "長崎県諫早市",
    "lat": "",
    "lng": "",
    "zoom": "",
    "image": ""
  },
  {
    "pidx": "4481",
    "jhno": "103",
    "pno": "19",
    "url": "https://japan-heritage.bunka.go.jp/ja/culturalproperties/result/5442/",
    "status": "未指定(民俗技術)",
    "name": "諫早おこし",
    "yomi": "",
    "spot": "長崎県諫早市",
    "lat": "",
    "lng": "",
    "zoom": "",
    "image": ""
  },
  {
    "pidx": "4482",
    "jhno": "103",
    "pno": "20",
    "url": "https://japan-heritage.bunka.go.jp/ja/culturalproperties/result/5443/",
    "status": "未指定（器具）",
    "name": "諫早おこし道具",
    "yomi": "",
    "spot": "長崎県諫早市",
    "lat": "",
    "lng": "",
    "zoom": "",
    "image": ""
  },
  {
    "pidx": "4483",
    "jhno": "103",
    "pno": "21",
    "url": "https://japan-heritage.bunka.go.jp/ja/culturalproperties/result/5444/",
    "status": "未指定",
    "name": "松原宿",
    "yomi": "",
    "spot": "長崎県大村市",
    "lat": "32.97528859999999",
    "lng": "129.944095",
    "zoom": "15",
    "image": "https://japan-heritage.bunka.go.jp/ja/datas/cache/images/2022/08/15/500x343_2ae395417f98b42be3d881be00011165_3310703463ec757b69ab25f04f0128fb5223fb50.jpeg"
  },
  {
    "pidx": "4484",
    "jhno": "103",
    "pno": "22",
    "url": "https://japan-heritage.bunka.go.jp/ja/culturalproperties/result/5445/",
    "status": "未指定(民俗技術)",
    "name": "へこはずしおこし",
    "yomi": "",
    "spot": "長崎県大村市",
    "lat": "",
    "lng": "",
    "zoom": "",
    "image": ""
  },
  {
    "pidx": "4485",
    "jhno": "103",
    "pno": "23",
    "url": "https://japan-heritage.bunka.go.jp/ja/culturalproperties/result/5446/",
    "status": "未指定（器具）",
    "name": "おこし製造道具",
    "yomi": "",
    "spot": "長崎県大村市",
    "lat": "32.97291600000001",
    "lng": "129.943355",
    "zoom": "15",
    "image": "https://japan-heritage.bunka.go.jp/ja/datas/cache/images/2022/08/15/500x343_2ae395417f98b42be3d881be00011165_beab2b1f1b7dd804ecf5beb0e49057cbfa787f68.jpeg"
  },
  {
    "pidx": "4486",
    "jhno": "103",
    "pno": "24",
    "url": "https://japan-heritage.bunka.go.jp/ja/culturalproperties/result/5447/",
    "status": "未指定(民俗技術)",
    "name": "大村寿司",
    "yomi": "",
    "spot": "長崎県大村市",
    "lat": "",
    "lng": "",
    "zoom": "",
    "image": ""
  },
  {
    "pidx": "4487",
    "jhno": "103",
    "pno": "25",
    "url": "https://japan-heritage.bunka.go.jp/ja/culturalproperties/result/5448/",
    "status": "国指定重要伝統的建造物群保存地区",
    "name": "嬉野市塩田津",
    "yomi": "",
    "spot": "佐賀県嬉野市",
    "lat": "33.131098000000044",
    "lng": "130.060831",
    "zoom": "15",
    "image": "https://japan-heritage.bunka.go.jp/ja/datas/cache/images/2022/08/15/500x343_2ae395417f98b42be3d881be00011165_2f88d2c4100077de5b68693b9c27c6009e7e08df.jpeg"
  },
  {
    "pidx": "4488",
    "jhno": "103",
    "pno": "26",
    "url": "https://japan-heritage.bunka.go.jp/ja/culturalproperties/result/5449/",
    "status": "未指定(民俗技術)",
    "name": "逸口香",
    "yomi": "",
    "spot": "佐賀県嬉野市",
    "lat": "",
    "lng": "",
    "zoom": "",
    "image": ""
  },
  {
    "pidx": "4489",
    "jhno": "103",
    "pno": "27",
    "url": "https://japan-heritage.bunka.go.jp/ja/culturalproperties/result/5450/",
    "status": "未指定(民俗技術)",
    "name": "金華糖",
    "yomi": "",
    "spot": "佐賀県嬉野市",
    "lat": "",
    "lng": "",
    "zoom": "",
    "image": ""
  },
  {
    "pidx": "4490",
    "jhno": "103",
    "pno": "28",
    "url": "https://japan-heritage.bunka.go.jp/ja/culturalproperties/result/5451/",
    "status": "未指定(民俗技術)",
    "name": "ふなんこぐい",
    "yomi": "",
    "spot": "佐賀県嬉野市",
    "lat": "",
    "lng": "",
    "zoom": "",
    "image": ""
  },
  {
    "pidx": "4491",
    "jhno": "103",
    "pno": "29",
    "url": "https://japan-heritage.bunka.go.jp/ja/culturalproperties/result/5452/",
    "status": "未指定(民俗技術)",
    "name": "砂糖酒",
    "yomi": "",
    "spot": "佐賀県嬉野市",
    "lat": "",
    "lng": "",
    "zoom": "",
    "image": ""
  },
  {
    "pidx": "4492",
    "jhno": "103",
    "pno": "30",
    "url": "https://japan-heritage.bunka.go.jp/ja/culturalproperties/result/5453/",
    "status": "未指定（伝統的建造物群）",
    "name": "牛津宿",
    "yomi": "",
    "spot": "佐賀県小城市",
    "lat": "33.24765719999999",
    "lng": "130.2043353",
    "zoom": "15",
    "image": "https://japan-heritage.bunka.go.jp/ja/datas/cache/images/2022/08/15/500x343_2ae395417f98b42be3d881be00011165_b8af4c9c8ed02e03aa36ee4c81aa7f3de0f8a2ea.jpeg"
  },
  {
    "pidx": "4493",
    "jhno": "103",
    "pno": "31",
    "url": "https://japan-heritage.bunka.go.jp/ja/culturalproperties/result/5454/",
    "status": "国登録有形文化財　22世紀に残す佐賀県遺産（建造物　他）",
    "name": "旧砂糖貯蔵庫及び製造道具等 （村岡総本舗羊羹資料館及び展示資料）",
    "yomi": "",
    "spot": "佐賀県小城市",
    "lat": "33.30128630000001",
    "lng": "130.20425489999997",
    "zoom": "15",
    "image": "https://japan-heritage.bunka.go.jp/ja/datas/cache/images/2022/08/15/500x343_2ae395417f98b42be3d881be00011165_fb711ea20e40e78b25f94c641a4d87baa81fb655.jpeg"
  },
  {
    "pidx": "4494",
    "jhno": "103",
    "pno": "32",
    "url": "https://japan-heritage.bunka.go.jp/ja/culturalproperties/result/5455/",
    "status": "22世紀に残す佐賀県遺産（建造物）",
    "name": "村岡総本舗小城本店",
    "yomi": "",
    "spot": "佐賀県小城市",
    "lat": "33.30128630000001",
    "lng": "130.20425489999997",
    "zoom": "15",
    "image": "https://japan-heritage.bunka.go.jp/ja/datas/cache/images/2022/08/15/500x343_2ae395417f98b42be3d881be00011165_137333af11603391c5722215e3de8db53fbb2f7b.jpeg"
  },
  {
    "pidx": "4495",
    "jhno": "103",
    "pno": "33",
    "url": "https://japan-heritage.bunka.go.jp/ja/culturalproperties/result/5456/",
    "status": "未指定(民俗技術)",
    "name": "小城羊羹",
    "yomi": "",
    "spot": "佐賀県小城市",
    "lat": "",
    "lng": "",
    "zoom": "",
    "image": ""
  },
  {
    "pidx": "4496",
    "jhno": "103",
    "pno": "34",
    "url": "https://japan-heritage.bunka.go.jp/ja/culturalproperties/result/5457/",
    "status": "未指定(伝統的建造物群)",
    "name": "柳町地区",
    "yomi": "",
    "spot": "佐賀県佐賀市",
    "lat": "33.254011299999995",
    "lng": "130.3077458",
    "zoom": "17",
    "image": "https://japan-heritage.bunka.go.jp/ja/datas/cache/images/2022/08/15/500x343_2ae395417f98b42be3d881be00011165_fbb6abed95014a9d2eb6830ab5ecb499c9d4239d.jpeg"
  },
  {
    "pidx": "4497",
    "jhno": "103",
    "pno": "35",
    "url": "https://japan-heritage.bunka.go.jp/ja/culturalproperties/result/5458/",
    "status": "未指定(民俗技術)",
    "name": "丸ぼうろ",
    "yomi": "",
    "spot": "佐賀県佐賀市",
    "lat": "",
    "lng": "",
    "zoom": "",
    "image": ""
  },
  {
    "pidx": "4498",
    "jhno": "103",
    "pno": "36",
    "url": "https://japan-heritage.bunka.go.jp/ja/culturalproperties/result/5459/",
    "status": "未指定(民俗技術)",
    "name": "ケシアド",
    "yomi": "",
    "spot": "佐賀県佐賀市",
    "lat": "",
    "lng": "",
    "zoom": "",
    "image": ""
  },
  {
    "pidx": "4499",
    "jhno": "103",
    "pno": "37",
    "url": "https://japan-heritage.bunka.go.jp/ja/culturalproperties/result/5460/",
    "status": "未指定(民俗技術)",
    "name": "寿賀台",
    "yomi": "",
    "spot": "佐賀県佐賀市",
    "lat": "",
    "lng": "",
    "zoom": "",
    "image": ""
  },
  {
    "pidx": "4500",
    "jhno": "103",
    "pno": "38",
    "url": "https://japan-heritage.bunka.go.jp/ja/culturalproperties/result/5461/",
    "status": "未指定(古文書)",
    "name": "菓子仕方控覚(鶴屋文書)",
    "yomi": "",
    "spot": "佐賀県佐賀市",
    "lat": "33.24841600000001",
    "lng": "130.29127299999996",
    "zoom": "15",
    "image": "https://japan-heritage.bunka.go.jp/ja/datas/cache/images/2022/08/15/500x343_2ae395417f98b42be3d881be00011165_f0c035a85939e3987cca2f2473149aff7db09e77.jpeg"
  },
  {
    "pidx": "4501",
    "jhno": "103",
    "pno": "39",
    "url": "https://japan-heritage.bunka.go.jp/ja/culturalproperties/result/5462/",
    "status": "未指定(古文書)",
    "name": "享和三年御菓子覚書(鶴屋文書)",
    "yomi": "",
    "spot": "佐賀県佐賀市",
    "lat": "33.24841600000001",
    "lng": "130.29127299999996",
    "zoom": "15",
    "image": "https://japan-heritage.bunka.go.jp/ja/datas/cache/images/2022/08/15/500x343_2ae395417f98b42be3d881be00011165_40af61d118c759ba4d51a653b0c79478e11f7e3c.jpeg"
  },
  {
    "pidx": "4502",
    "jhno": "103",
    "pno": "40",
    "url": "https://japan-heritage.bunka.go.jp/ja/culturalproperties/result/5463/",
    "status": "未指定(古文書)",
    "name": "御菓子覚書(鶴屋文書)",
    "yomi": "",
    "spot": "佐賀県佐賀市",
    "lat": "33.24841600000001",
    "lng": "130.29127299999996",
    "zoom": "15",
    "image": "https://japan-heritage.bunka.go.jp/ja/datas/cache/images/2022/08/15/500x343_2ae395417f98b42be3d881be00011165_21617e6b78e19491e9f716366d10d71c6e8dc2b8.jpeg"
  },
  {
    "pidx": "4503",
    "jhno": "103",
    "pno": "41",
    "url": "https://japan-heritage.bunka.go.jp/ja/culturalproperties/result/5464/",
    "status": "未指定(古文書)",
    "name": "諸願書御菓子日記帳(鶴屋文書)",
    "yomi": "",
    "spot": "佐賀県佐賀市",
    "lat": "33.24841600000001",
    "lng": "130.29127299999996",
    "zoom": "15",
    "image": "https://japan-heritage.bunka.go.jp/ja/datas/cache/images/2022/08/15/500x343_2ae395417f98b42be3d881be00011165_d12d8248a5d5dbc4f268a5189eba959e591b9e3e.jpeg"
  },
  {
    "pidx": "4504",
    "jhno": "103",
    "pno": "42",
    "url": "https://japan-heritage.bunka.go.jp/ja/culturalproperties/result/5465/",
    "status": "未指定(古文書)",
    "name": "菓子製造法帳（北島文書）",
    "yomi": "",
    "spot": "佐賀県佐賀市",
    "lat": "33.25352946393909",
    "lng": "130.29942123717396",
    "zoom": "17",
    "image": "https://japan-heritage.bunka.go.jp/ja/datas/cache/images/2022/08/15/500x343_2ae395417f98b42be3d881be00011165_3716246e20584c5dff2a9fe8ddedb6998c43c34c.jpeg"
  },
  {
    "pidx": "4505",
    "jhno": "103",
    "pno": "43",
    "url": "https://japan-heritage.bunka.go.jp/ja/culturalproperties/result/5466/",
    "status": "未指定(伝統的建造物群)",
    "name": "内野宿",
    "yomi": "",
    "spot": "福岡県飯塚市",
    "lat": "33.535603800000004",
    "lng": "130.63976170000004",
    "zoom": "15",
    "image": "https://japan-heritage.bunka.go.jp/ja/datas/cache/images/2022/08/15/500x343_2ae395417f98b42be3d881be00011165_965e9195622d52fe106b5ebeced3c66e94f5359b.jpeg"
  },
  {
    "pidx": "4506",
    "jhno": "103",
    "pno": "44",
    "url": "https://japan-heritage.bunka.go.jp/ja/culturalproperties/result/5467/",
    "status": "未指定(民俗技術)",
    "name": "千鳥饅頭",
    "yomi": "",
    "spot": "福岡県飯塚市",
    "lat": "",
    "lng": "",
    "zoom": "",
    "image": ""
  },
  {
    "pidx": "4507",
    "jhno": "103",
    "pno": "45",
    "url": "https://japan-heritage.bunka.go.jp/ja/culturalproperties/result/5468/",
    "status": "未指定(民俗技術)",
    "name": "名菓ひよ子",
    "yomi": "",
    "spot": "福岡県飯塚市",
    "lat": "",
    "lng": "",
    "zoom": "",
    "image": ""
  },
  {
    "pidx": "4508",
    "jhno": "103",
    "pno": "46",
    "url": "https://japan-heritage.bunka.go.jp/ja/culturalproperties/result/5469/",
    "status": "未指定(民俗技術)",
    "name": "なんばん往来",
    "yomi": "",
    "spot": "福岡県飯塚市",
    "lat": "",
    "lng": "",
    "zoom": "",
    "image": ""
  },
  {
    "pidx": "4509",
    "jhno": "103",
    "pno": "47",
    "url": "https://japan-heritage.bunka.go.jp/ja/culturalproperties/result/5470/",
    "status": "県指定史跡",
    "name": "福聚寺",
    "yomi": "",
    "spot": "福岡県北九州市",
    "lat": "33.87045000000003",
    "lng": "130.902895",
    "zoom": "15",
    "image": "https://japan-heritage.bunka.go.jp/ja/datas/cache/images/2022/08/15/500x343_2ae395417f98b42be3d881be00011165_8cf1ed2ff5c942032066a783e1ca1612019b81d9.jpeg"
  },
  {
    "pidx": "4510",
    "jhno": "103",
    "pno": "48",
    "url": "https://japan-heritage.bunka.go.jp/ja/culturalproperties/result/5471/",
    "status": "未指定(民俗技術)",
    "name": "小菊饅頭",
    "yomi": "",
    "spot": "福岡県北九州市",
    "lat": "",
    "lng": "",
    "zoom": "",
    "image": ""
  },
  {
    "pidx": "4511",
    "jhno": "103",
    "pno": "49",
    "url": "https://japan-heritage.bunka.go.jp/ja/culturalproperties/result/5472/",
    "status": "未指定(民俗技術)",
    "name": "栗饅頭",
    "yomi": "",
    "spot": "福岡県北九州市",
    "lat": "",
    "lng": "",
    "zoom": "",
    "image": ""
  },
  {
    "pidx": "4512",
    "jhno": "103",
    "pno": "50",
    "url": "https://japan-heritage.bunka.go.jp/ja/culturalproperties/result/5473/",
    "status": "未指定(民俗技術)",
    "name": "金平糖",
    "yomi": "",
    "spot": "福岡県北九州市",
    "lat": "",
    "lng": "",
    "zoom": "",
    "image": ""
  },
  {
    "pidx": "4513",
    "jhno": "103",
    "pno": "51",
    "url": "https://japan-heritage.bunka.go.jp/ja/culturalproperties/result/5474/",
    "status": "未指定(民俗技術)",
    "name": "くろがね羊羹",
    "yomi": "",
    "spot": "福岡県北九州市",
    "lat": "",
    "lng": "",
    "zoom": "",
    "image": ""
  },
  {
    "pidx": "4514",
    "jhno": "103",
    "pno": "52",
    "url": "https://japan-heritage.bunka.go.jp/ja/culturalproperties/result/5475/",
    "status": "未指定(史跡)",
    "name": "常盤橋",
    "yomi": "",
    "spot": "福岡県北九州市",
    "lat": "33.886353000000014",
    "lng": "130.87749909999997",
    "zoom": "15",
    "image": "https://japan-heritage.bunka.go.jp/ja/datas/cache/images/2022/08/15/500x343_2ae395417f98b42be3d881be00011165_9dd44084bde8cfeb35015ce5aa18e2c7812c0971.jpeg"
  }
]