[
  {
    "pidx": "34",
    "jhno": "3",
    "pno": "1",
    "url": "https://japan-heritage.bunka.go.jp/ja/culturalproperties/result/260/",
    "status": "国宝・重要文化財（建造物）",
    "name": "瑞龍寺",
    "yomi": "ずいりゅうじ",
    "spot": "富山県高岡市",
    "lat": "36.735622199999995",
    "lng": "137.01046819999988",
    "zoom": "19",
    "image": "https://japan-heritage.bunka.go.jp/ja/datas/cache/images/2022/08/09/500x343_2ae395417f98b42be3d881be00011165_582fe9e45729064b39152c88d6d74c7a47610053.jpg"
  },
  {
    "pidx": "35",
    "jhno": "3",
    "pno": "2",
    "url": "https://japan-heritage.bunka.go.jp/ja/culturalproperties/result/262/",
    "status": "国指定史跡",
    "name": "前田利長墓所",
    "yomi": "まえだとしながぼしょ",
    "spot": "富山県高岡市",
    "lat": "36.73763739999994",
    "lng": "137.02304010000003",
    "zoom": "19",
    "image": "https://japan-heritage.bunka.go.jp/ja/datas/cache/images/2022/08/09/500x343_2ae395417f98b42be3d881be00011165_11b31982b78b9b93659c859595e79e585b3f9564.jpg"
  },
  {
    "pidx": "36",
    "jhno": "3",
    "pno": "3",
    "url": "https://japan-heritage.bunka.go.jp/ja/culturalproperties/result/264/",
    "status": "市指定文化財（建造物）",
    "name": "五福町神明社本殿",
    "yomi": "ごふくまちしんめいしゃほんでん",
    "spot": "富山県高岡市",
    "lat": "36.757973600000014",
    "lng": "137.0138068",
    "zoom": "19",
    "image": "https://japan-heritage.bunka.go.jp/ja/datas/cache/images/2022/08/09/500x343_2ae395417f98b42be3d881be00011165_ce965191dd6a6d77ffa5c8bc40e01c7113f667a1.jpg"
  },
  {
    "pidx": "37",
    "jhno": "3",
    "pno": "4",
    "url": "https://japan-heritage.bunka.go.jp/ja/culturalproperties/result/266/",
    "status": "市指定文化財（建造物）",
    "name": "大手町神明社拝殿",
    "yomi": "おおてまちしんめいしゃはいでん",
    "spot": "富山県高岡市",
    "lat": "36.74466690000001",
    "lng": "137.01869050000005",
    "zoom": "19",
    "image": "https://japan-heritage.bunka.go.jp/ja/datas/cache/images/2022/08/09/500x343_2ae395417f98b42be3d881be00011165_f55c36910176aacd2253bfdad9c551e67e9886b5.jpg"
  },
  {
    "pidx": "38",
    "jhno": "3",
    "pno": "5",
    "url": "https://japan-heritage.bunka.go.jp/ja/culturalproperties/result/268/",
    "status": "国指定史跡",
    "name": "高岡城跡",
    "yomi": "たかおかじょうあと",
    "spot": "富山県高岡市",
    "lat": "36.74851970000001",
    "lng": "137.02081699999997",
    "zoom": "19",
    "image": "https://japan-heritage.bunka.go.jp/ja/datas/cache/images/2022/08/09/500x343_2ae395417f98b42be3d881be00011165_9c2f637215d492d166c77ca8dad2012fee5b4a9e.jpg"
  },
  {
    "pidx": "39",
    "jhno": "3",
    "pno": "6",
    "url": "https://japan-heritage.bunka.go.jp/ja/culturalproperties/result/270/",
    "status": "市指定文化財（古文書）",
    "name": "前田利長公御親書",
    "yomi": "",
    "spot": "富山県高岡市",
    "lat": "36.76225870000004",
    "lng": "137.01330959999996",
    "zoom": "19",
    "image": "https://japan-heritage.bunka.go.jp/ja/datas/cache/images/2022/08/09/500x343_2ae395417f98b42be3d881be00011165_95a2fdbf4e26886955e1745e2d8c13ec7bd54c61.jpg"
  },
  {
    "pidx": "40",
    "jhno": "3",
    "pno": "7",
    "url": "https://japan-heritage.bunka.go.jp/ja/culturalproperties/result/272/",
    "status": "重要有形民俗文化財",
    "name": "高岡御車山",
    "yomi": "たかおかみくるまやま",
    "spot": "富山県高岡市",
    "lat": "36.74338360000004",
    "lng": "137.0120941",
    "zoom": "19",
    "image": "https://japan-heritage.bunka.go.jp/ja/datas/cache/images/2022/08/09/500x343_2ae395417f98b42be3d881be00011165_2c1cb8a78e20b9931945a32d3f86f4f517f0e03b.jpg"
  },
  {
    "pidx": "41",
    "jhno": "3",
    "pno": "8",
    "url": "https://japan-heritage.bunka.go.jp/ja/culturalproperties/result/274/",
    "status": "重要無形民俗文化財",
    "name": "高岡御車山祭の御車山行事",
    "yomi": "たかおかみくるまやままつりのみくるまやまぎょうじ",
    "spot": "富山県高岡市",
    "lat": "",
    "lng": "",
    "zoom": "",
    "image": ""
  },
  {
    "pidx": "42",
    "jhno": "3",
    "pno": "9",
    "url": "https://japan-heritage.bunka.go.jp/ja/culturalproperties/result/276/",
    "status": "未指定",
    "name": "与四兵衛顕彰碑（弥眞進大人命旧跡）",
    "yomi": "",
    "spot": "富山県高岡市",
    "lat": "36.745002800000044",
    "lng": "137.00824439999997",
    "zoom": "19",
    "image": "https://japan-heritage.bunka.go.jp/ja/datas/cache/images/2022/08/09/500x343_2ae395417f98b42be3d881be00011165_799865e7c2e7353ca43e1f802d987f078812799f.jpg"
  },
  {
    "pidx": "43",
    "jhno": "3",
    "pno": "10",
    "url": "https://japan-heritage.bunka.go.jp/ja/culturalproperties/result/278/",
    "status": "市指定文化財（古文書）",
    "name": "明和八年製高岡町図",
    "yomi": "",
    "spot": "富山県高岡市",
    "lat": "36.74291700000001",
    "lng": "137.01426889999993",
    "zoom": "19",
    "image": "https://japan-heritage.bunka.go.jp/ja/datas/cache/images/2022/08/09/500x343_2ae395417f98b42be3d881be00011165_47450e175bf751623c2cb6aa3354c268617e5e49.jpg"
  },
  {
    "pidx": "44",
    "jhno": "3",
    "pno": "11",
    "url": "https://japan-heritage.bunka.go.jp/ja/culturalproperties/result/280/",
    "status": "重要伝統的建造物群保存地区",
    "name": "山町筋重要伝統的建造物群保存地区",
    "yomi": "やまちょうすじじゅうようでんとうてきけんぞうぶつぐんほぞんちく",
    "spot": "富山県高岡市",
    "lat": "36.74656370000004",
    "lng": "137.0100025",
    "zoom": "19",
    "image": "https://japan-heritage.bunka.go.jp/ja/datas/cache/images/2022/08/09/500x343_2ae395417f98b42be3d881be00011165_eee04c8ef9cafdee62bb513bd782b9e13de1dd22.jpg"
  },
  {
    "pidx": "45",
    "jhno": "3",
    "pno": "12",
    "url": "https://japan-heritage.bunka.go.jp/ja/culturalproperties/result/282/",
    "status": "重要文化財（建造物）",
    "name": "菅野家住宅",
    "yomi": "すがのけじゅうたく",
    "spot": "富山県高岡市",
    "lat": "36.74791079999997",
    "lng": "137.0117077",
    "zoom": "19",
    "image": "https://japan-heritage.bunka.go.jp/ja/datas/cache/images/2022/08/09/500x343_2ae395417f98b42be3d881be00011165_21f8e3f99514b8a8e6f1120f9d7f13116f7e7a43.jpg"
  },
  {
    "pidx": "46",
    "jhno": "3",
    "pno": "13",
    "url": "https://japan-heritage.bunka.go.jp/ja/culturalproperties/result/284/",
    "status": "県指定文化財（建造物）",
    "name": "筏井家住宅",
    "yomi": "いかだいけじゅうたく",
    "spot": "富山県高岡市",
    "lat": "36.74721040000006",
    "lng": "137.0114089",
    "zoom": "19",
    "image": "https://japan-heritage.bunka.go.jp/ja/datas/cache/images/2022/08/09/500x343_2ae395417f98b42be3d881be00011165_8888933b1be7b8d259bda2d19cce5de532a5edb8.jpg"
  },
  {
    "pidx": "47",
    "jhno": "3",
    "pno": "14",
    "url": "https://japan-heritage.bunka.go.jp/ja/culturalproperties/result/286/",
    "status": "市指定文化財（建造物）",
    "name": "土蔵造りのまち資料館（旧室崎家住宅）",
    "yomi": "",
    "spot": "富山県高岡市",
    "lat": "36.74850189999999",
    "lng": "137.01338529999998",
    "zoom": "19",
    "image": "https://japan-heritage.bunka.go.jp/ja/datas/cache/images/2022/08/09/500x343_2ae395417f98b42be3d881be00011165_f39f38b9d5a30c65fa769d3041552a623b46ecf9.jpg"
  },
  {
    "pidx": "48",
    "jhno": "3",
    "pno": "15",
    "url": "https://japan-heritage.bunka.go.jp/ja/culturalproperties/result/288/",
    "status": "重要伝統的建造物群保存地区",
    "name": "金屋町重要伝統的建造物群保存地区",
    "yomi": "かなやまちじゅうようでんとうてきけんぞうぶつぐんほぞんちく",
    "spot": "富山県高岡市",
    "lat": "36.75083260000005",
    "lng": "137.00545269999998",
    "zoom": "19",
    "image": "https://japan-heritage.bunka.go.jp/ja/datas/cache/images/2022/08/09/500x343_2ae395417f98b42be3d881be00011165_2622e1373ef2afb4975474a0d01ff17fd7f160da.jpg"
  },
  {
    "pidx": "49",
    "jhno": "3",
    "pno": "16",
    "url": "https://japan-heritage.bunka.go.jp/ja/culturalproperties/result/290/",
    "status": "市指定文化財（古文書）",
    "name": "仁安の御綸旨",
    "yomi": "にんあんのごりんじ",
    "spot": "富山県高岡市",
    "lat": "36.75056050000002",
    "lng": "137.00734409999995",
    "zoom": "19",
    "image": "https://japan-heritage.bunka.go.jp/ja/datas/cache/images/2022/08/09/500x343_2ae395417f98b42be3d881be00011165_7171c0d16a3364110cebaf5ff9c2c692c754069c.jpg"
  },
  {
    "pidx": "50",
    "jhno": "3",
    "pno": "17",
    "url": "https://japan-heritage.bunka.go.jp/ja/culturalproperties/result/292/",
    "status": "市指定文化財（古文書）",
    "name": "前田利長書状",
    "yomi": "",
    "spot": "富山県高岡市",
    "lat": "36.746566000000016",
    "lng": "137.02087980000002",
    "zoom": "19",
    "image": "https://japan-heritage.bunka.go.jp/ja/datas/cache/images/2022/08/09/500x343_2ae395417f98b42be3d881be00011165_53283498054a6486750f3f8f0b20f993eab1f52c.jpg"
  },
  {
    "pidx": "51",
    "jhno": "3",
    "pno": "18",
    "url": "https://japan-heritage.bunka.go.jp/ja/culturalproperties/result/294/",
    "status": "登録文化財（建造物）",
    "name": "有礒正八幡宮（本殿・釣殿・拝殿及び弊殿）",
    "yomi": "ありそしょうはちまんぐう【ほんでん・つりどの・はいでん・へいでん】",
    "spot": "富山県高岡市",
    "lat": "36.74977400000003",
    "lng": "137.003025",
    "zoom": "19",
    "image": "https://japan-heritage.bunka.go.jp/ja/datas/cache/images/2022/08/09/500x343_2ae395417f98b42be3d881be00011165_3ad97b2bc1184600de6653697e672898bb89a269.jpg"
  },
  {
    "pidx": "52",
    "jhno": "3",
    "pno": "19",
    "url": "https://japan-heritage.bunka.go.jp/ja/culturalproperties/result/296/",
    "status": "市指定文化財（彫刻）",
    "name": "銅造阿弥陀如来坐像",
    "yomi": "どうぞうあみだにょらいざぞう",
    "spot": "富山県高岡市",
    "lat": "36.745652899999996",
    "lng": "137.01721840000002",
    "zoom": "19",
    "image": "https://japan-heritage.bunka.go.jp/ja/datas/cache/images/2022/08/09/500x343_2ae395417f98b42be3d881be00011165_152c75a781efff17a98bbe48a5f1c63ec972dc84.jpg"
  },
  {
    "pidx": "53",
    "jhno": "3",
    "pno": "20",
    "url": "https://japan-heritage.bunka.go.jp/ja/culturalproperties/result/298/",
    "status": "登録有形民俗文化財",
    "name": "高岡鋳物の製作用具及び製品",
    "yomi": "たかおかいもののせいさくようぐおよびせいひん",
    "spot": "富山県高岡市",
    "lat": "36.750563000000014",
    "lng": "137.0062250000001",
    "zoom": "19",
    "image": "https://japan-heritage.bunka.go.jp/ja/datas/cache/images/2022/08/09/500x343_2ae395417f98b42be3d881be00011165_7690cf7c8df7ba796492a2e5c3944b988b6e49e9.jpg"
  },
  {
    "pidx": "54",
    "jhno": "3",
    "pno": "21",
    "url": "https://japan-heritage.bunka.go.jp/ja/culturalproperties/result/300/",
    "status": "未指定",
    "name": "御印祭",
    "yomi": "ごいんさい",
    "spot": "富山県高岡市",
    "lat": "",
    "lng": "",
    "zoom": "",
    "image": ""
  },
  {
    "pidx": "55",
    "jhno": "3",
    "pno": "22",
    "url": "https://japan-heritage.bunka.go.jp/ja/culturalproperties/result/302/",
    "status": "登録文化財（建造物）",
    "name": "旧南部鋳造所キュポラ及び煙突",
    "yomi": "きゅうなんぶちゅうぞうじょきゅぽらおよびえんとつ",
    "spot": "富山県高岡市",
    "lat": "36.752057499999985",
    "lng": "137.00604139999993",
    "zoom": "19",
    "image": "https://japan-heritage.bunka.go.jp/ja/datas/cache/images/2022/08/09/500x343_2ae395417f98b42be3d881be00011165_4e6ff78fc96ae7ef24394bdbda31beca81b01791.jpg"
  },
  {
    "pidx": "56",
    "jhno": "3",
    "pno": "23",
    "url": "https://japan-heritage.bunka.go.jp/ja/culturalproperties/result/304/",
    "status": "市指定有形民俗文化財",
    "name": "梵鐘龍頭木型",
    "yomi": "",
    "spot": "富山県高岡市",
    "lat": "",
    "lng": "",
    "zoom": "",
    "image": ""
  },
  {
    "pidx": "57",
    "jhno": "3",
    "pno": "24",
    "url": "https://japan-heritage.bunka.go.jp/ja/culturalproperties/result/306/",
    "status": "市指定文化財（建造物）",
    "name": "戸出御旅屋の門",
    "yomi": "",
    "spot": "富山県高岡市",
    "lat": "36.680953700000025",
    "lng": "136.9802566",
    "zoom": "19",
    "image": "https://japan-heritage.bunka.go.jp/ja/datas/cache/images/2022/08/09/500x343_2ae395417f98b42be3d881be00011165_5f9478c9937407cc6617d499f5b5edb675819b7a.jpg"
  },
  {
    "pidx": "58",
    "jhno": "3",
    "pno": "25",
    "url": "https://japan-heritage.bunka.go.jp/ja/culturalproperties/result/308/",
    "status": "国宝・重要文化財（建造物）",
    "name": "勝興寺",
    "yomi": "しょうこうじ",
    "spot": "富山県高岡市",
    "lat": "36.79314920000001",
    "lng": "137.0526763",
    "zoom": "19",
    "image": "https://japan-heritage.bunka.go.jp/ja/datas/cache/images/2022/08/09/500x343_2ae395417f98b42be3d881be00011165_bc003ea4062c3908cd19a8e63c17fd3ca004e7fa.jpg"
  },
  {
    "pidx": "59",
    "jhno": "3",
    "pno": "26",
    "url": "https://japan-heritage.bunka.go.jp/ja/culturalproperties/result/310/",
    "status": "未指定",
    "name": "伏木港（伏木浦）",
    "yomi": "",
    "spot": "富山県高岡市",
    "lat": "36.791859000000024",
    "lng": "137.06627679999997",
    "zoom": "19",
    "image": "https://japan-heritage.bunka.go.jp/ja/datas/cache/images/2022/08/09/500x343_2ae395417f98b42be3d881be00011165_e40b81637123bc5d5eb001f5ce11841b89a6e937.jpg"
  },
  {
    "pidx": "60",
    "jhno": "3",
    "pno": "27",
    "url": "https://japan-heritage.bunka.go.jp/ja/culturalproperties/result/312/",
    "status": "市指定文化財（建造物）",
    "name": "伏木北前船資料館（旧秋元家住宅）",
    "yomi": "",
    "spot": "富山県高岡市",
    "lat": "36.794328000000014",
    "lng": "137.057871",
    "zoom": "19",
    "image": "https://japan-heritage.bunka.go.jp/ja/datas/cache/images/2022/08/09/500x343_2ae395417f98b42be3d881be00011165_663ed6904d759adc71eb938af175c6ca2052eaec.jpg"
  },
  {
    "pidx": "61",
    "jhno": "3",
    "pno": "28",
    "url": "https://japan-heritage.bunka.go.jp/ja/culturalproperties/result/314/",
    "status": "登録文化財（建造物）",
    "name": "棚田家住宅",
    "yomi": "たなだけじゅうたく",
    "spot": "富山県高岡市",
    "lat": "36.79316199999998",
    "lng": "137.05904050000004",
    "zoom": "19",
    "image": "https://japan-heritage.bunka.go.jp/ja/datas/cache/images/2022/08/09/500x343_2ae395417f98b42be3d881be00011165_6c5eaa40b2a3b2550a45276dd124b8188c9387d1.jpg"
  },
  {
    "pidx": "62",
    "jhno": "3",
    "pno": "29",
    "url": "https://japan-heritage.bunka.go.jp/ja/culturalproperties/result/316/",
    "status": "登録文化財（建造物）",
    "name": "能松家住宅",
    "yomi": "のうまつけじゅうたく",
    "spot": "富山県高岡市",
    "lat": "36.78010749999998",
    "lng": "137.05616099999997",
    "zoom": "19",
    "image": "https://japan-heritage.bunka.go.jp/ja/datas/cache/images/2022/08/09/500x343_2ae395417f98b42be3d881be00011165_17d4aaa82969c3a3b70005048ef5af457e542510.jpg"
  },
  {
    "pidx": "63",
    "jhno": "3",
    "pno": "30",
    "url": "https://japan-heritage.bunka.go.jp/ja/culturalproperties/result/318/",
    "status": "登録文化財（建造物）",
    "name": "有藤家住宅",
    "yomi": "ありとうけじゅうたく",
    "spot": "富山県高岡市",
    "lat": "36.7794187",
    "lng": "137.05530829999995",
    "zoom": "19",
    "image": "https://japan-heritage.bunka.go.jp/ja/datas/cache/images/2022/08/09/500x343_2ae395417f98b42be3d881be00011165_ffab7fd370a8615b0a9b25f52c75ed041c396021.jpg"
  },
  {
    "pidx": "64",
    "jhno": "3",
    "pno": "31",
    "url": "https://japan-heritage.bunka.go.jp/ja/culturalproperties/result/320/",
    "status": "登録文化財（建造物）",
    "name": "高岡商工会議所伏木支所",
    "yomi": "たかおかしょうこうかいぎしょふしきししょ",
    "spot": "富山県高岡市",
    "lat": "36.79558100000001",
    "lng": "137.062318",
    "zoom": "19",
    "image": "https://japan-heritage.bunka.go.jp/ja/datas/cache/images/2022/08/09/500x343_2ae395417f98b42be3d881be00011165_2f7ba1a7ab7f561b23d8e1798fd9d1da0348e001.jpg"
  },
  {
    "pidx": "65",
    "jhno": "3",
    "pno": "32",
    "url": "https://japan-heritage.bunka.go.jp/ja/culturalproperties/result/322/",
    "status": "登録文化財（建造物）",
    "name": "伏木気象資料館（旧伏木側候所庁舎・測風塔）",
    "yomi": "ふしききしょうしりょうかん（きゅうふしきそっこうじょちょうしゃ・そくふうとう）",
    "spot": "富山県高岡市",
    "lat": "36.79235859999997",
    "lng": "137.05581440000003",
    "zoom": "19",
    "image": "https://japan-heritage.bunka.go.jp/ja/datas/cache/images/2022/08/09/500x343_2ae395417f98b42be3d881be00011165_1eaa8e92bb8aecdefcd50a35dac535e38fc82f3a.jpg"
  },
  {
    "pidx": "66",
    "jhno": "3",
    "pno": "33",
    "url": "https://japan-heritage.bunka.go.jp/ja/culturalproperties/result/324/",
    "status": "登録文化財（建造物）",
    "name": "丸谷家住宅",
    "yomi": "まるやけじゅうたく",
    "spot": "富山県高岡市",
    "lat": "36.779338100000025",
    "lng": "137.05511109999995",
    "zoom": "19",
    "image": "https://japan-heritage.bunka.go.jp/ja/datas/cache/images/2022/08/09/500x343_2ae395417f98b42be3d881be00011165_1ca6ee42bf77362124fe560b143661d33ef66976.jpg"
  },
  {
    "pidx": "67",
    "jhno": "3",
    "pno": "34",
    "url": "https://japan-heritage.bunka.go.jp/ja/culturalproperties/result/326/",
    "status": "登録文化財（建造物）",
    "name": "佐野家住宅",
    "yomi": "さのけじゅうたく",
    "spot": "富山県高岡市",
    "lat": "36.745930400000006",
    "lng": "137.00816940000007",
    "zoom": "19",
    "image": "https://japan-heritage.bunka.go.jp/ja/datas/cache/images/2022/08/09/500x343_2ae395417f98b42be3d881be00011165_38495589836a3bdcc25e2baac417f858f102be85.jpg"
  },
  {
    "pidx": "68",
    "jhno": "3",
    "pno": "35",
    "url": "https://japan-heritage.bunka.go.jp/ja/culturalproperties/result/328/",
    "status": "登録文化財（建造物）",
    "name": "清都酒造場",
    "yomi": "きよとしゅぞうじょう",
    "spot": "富山県高岡市",
    "lat": "36.75631550000003",
    "lng": "137.0136986",
    "zoom": "19",
    "image": "https://japan-heritage.bunka.go.jp/ja/datas/cache/images/2022/08/09/500x343_2ae395417f98b42be3d881be00011165_a48d0084bb6d8f8c9175095eb6c4954a19980607.jpg"
  },
  {
    "pidx": "69",
    "jhno": "3",
    "pno": "36",
    "url": "https://japan-heritage.bunka.go.jp/ja/culturalproperties/result/330/",
    "status": "重要無形民俗文化財",
    "name": "越中福岡の菅笠製作技術",
    "yomi": "えっちゅうふくおかのすげがさせいさくぎじゅつ",
    "spot": "富山県高岡市",
    "lat": "",
    "lng": "",
    "zoom": "",
    "image": ""
  },
  {
    "pidx": "70",
    "jhno": "3",
    "pno": "37",
    "url": "https://japan-heritage.bunka.go.jp/ja/culturalproperties/result/332/",
    "status": "未指定(景観形成重点区域)",
    "name": "菅笠問屋の町並み",
    "yomi": "",
    "spot": "富山県高岡市",
    "lat": "",
    "lng": "",
    "zoom": "",
    "image": ""
  },
  {
    "pidx": "71",
    "jhno": "3",
    "pno": "38",
    "url": "https://japan-heritage.bunka.go.jp/ja/culturalproperties/result/6500/",
    "status": "重要伝統的建造物群保存地区",
    "name": "吉久重要伝統的建造物群保存地区",
    "yomi": "よしひさじゅうようでんとうてきけんぞうぶつぐんほぞんちく",
    "spot": "富山県高岡市",
    "lat": "36.7794603",
    "lng": "137.0539623",
    "zoom": "17",
    "image": "https://japan-heritage.bunka.go.jp/ja/datas/cache/images/2022/11/21/500x343_2ae395417f98b42be3d881be00011165_0b9a2721da4622e64f986b1e4925566755152f33.jpg"
  }
]