[
  {
    "pidx": "1314",
    "jhno": "32",
    "pno": "1",
    "url": "https://japan-heritage.bunka.go.jp/ja/culturalproperties/result/2179/",
    "status": "国重要無形民俗",
    "name": "河内祭の御舟行事",
    "yomi": "",
    "spot": "和歌山県串本町",
    "lat": "",
    "lng": "",
    "zoom": "",
    "image": ""
  },
  {
    "pidx": "1315",
    "jhno": "32",
    "pno": "2",
    "url": "https://japan-heritage.bunka.go.jp/ja/culturalproperties/result/2180/",
    "status": "国名勝",
    "name": "九龍島",
    "yomi": "",
    "spot": "和歌山県串本町",
    "lat": "33.50444700000003",
    "lng": "135.82562800000005",
    "zoom": "17",
    "image": "https://japan-heritage.bunka.go.jp/ja/datas/cache/images/2022/08/15/500x343_2ae395417f98b42be3d881be00011165_0bdd5b27cc85e8b8b68689bb1e6ba2bedcb5ceb5.jpeg"
  },
  {
    "pidx": "1316",
    "jhno": "32",
    "pno": "3",
    "url": "https://japan-heritage.bunka.go.jp/ja/culturalproperties/result/2181/",
    "status": "未指定",
    "name": "潮岬の鯨山見",
    "yomi": "",
    "spot": "和歌山県串本町",
    "lat": "33.4384966",
    "lng": "135.75286389999997",
    "zoom": "17",
    "image": "https://japan-heritage.bunka.go.jp/ja/datas/cache/images/2022/08/15/500x343_2ae395417f98b42be3d881be00011165_0a84573f5e052e2d2e737c396c2084708f2ee78f.jpeg"
  },
  {
    "pidx": "1317",
    "jhno": "32",
    "pno": "4",
    "url": "https://japan-heritage.bunka.go.jp/ja/culturalproperties/result/5723/",
    "status": "未指定",
    "name": "樫野崎の鯨山見",
    "yomi": "",
    "spot": "和歌山県串本町",
    "lat": "33.472010999999995",
    "lng": "135.8623366",
    "zoom": "17",
    "image": "https://japan-heritage.bunka.go.jp/ja/datas/cache/images/2022/09/09/500x343_2ae395417f98b42be3d881be00011165_8da90ff2b8b4b179829f7e66dd112ce076810ed2.jpg"
  },
  {
    "pidx": "1318",
    "jhno": "32",
    "pno": "5",
    "url": "https://japan-heritage.bunka.go.jp/ja/culturalproperties/result/5725/",
    "status": "未指定",
    "name": "串本町史編纂資料",
    "yomi": "",
    "spot": "和歌山県串本町",
    "lat": "33.47201630000001",
    "lng": "135.78393360000004",
    "zoom": "17",
    "image": "https://japan-heritage.bunka.go.jp/ja/datas/cache/images/2022/09/09/500x343_2ae395417f98b42be3d881be00011165_666f5139fd2684b050449ed35f60aeb42679b936.jpg"
  },
  {
    "pidx": "1319",
    "jhno": "32",
    "pno": "6",
    "url": "https://japan-heritage.bunka.go.jp/ja/culturalproperties/result/5727/",
    "status": "未指定",
    "name": "有田八幡神社寄進札",
    "yomi": "",
    "spot": "和歌山県串本町",
    "lat": "34.67298110000004",
    "lng": "132.5313462",
    "zoom": "17",
    "image": "https://japan-heritage.bunka.go.jp/ja/datas/cache/images/2022/09/09/500x343_2ae395417f98b42be3d881be00011165_d3d996f67691da5774855962a744aca9748daff2.jpg"
  },
  {
    "pidx": "1320",
    "jhno": "32",
    "pno": "7",
    "url": "https://japan-heritage.bunka.go.jp/ja/culturalproperties/result/5729/",
    "status": "未指定",
    "name": "古座組鯨方石宝",
    "yomi": "",
    "spot": "和歌山県串本町",
    "lat": "33.51444980000002",
    "lng": "135.8300258",
    "zoom": "17",
    "image": "https://japan-heritage.bunka.go.jp/ja/datas/cache/images/2022/09/09/500x343_2ae395417f98b42be3d881be00011165_59f2208d30632308983501dec3e757cf457eb903.jpg"
  },
  {
    "pidx": "1321",
    "jhno": "32",
    "pno": "8",
    "url": "https://japan-heritage.bunka.go.jp/ja/culturalproperties/result/2182/",
    "status": "県史跡",
    "name": "捕鯨の祖 和田頼元墓",
    "yomi": "",
    "spot": "和歌山県太地町",
    "lat": "33.59148680000003",
    "lng": "135.94400629999996",
    "zoom": "19",
    "image": "https://japan-heritage.bunka.go.jp/ja/datas/cache/images/2022/09/09/500x343_2ae395417f98b42be3d881be00011165_cfa120e153dd7ea40536f0c771ece05b689e5e10.jpg"
  },
  {
    "pidx": "1322",
    "jhno": "32",
    "pno": "9",
    "url": "https://japan-heritage.bunka.go.jp/ja/culturalproperties/result/2183/",
    "status": "県無形民俗",
    "name": "太地のくじら踊",
    "yomi": "",
    "spot": "和歌山県太地町",
    "lat": "",
    "lng": "",
    "zoom": "",
    "image": ""
  },
  {
    "pidx": "1323",
    "jhno": "32",
    "pno": "10",
    "url": "https://japan-heritage.bunka.go.jp/ja/culturalproperties/result/2184/",
    "status": "町指定（建造物）",
    "name": "飛鳥神社",
    "yomi": "",
    "spot": "和歌山県太地町",
    "lat": "33.59202399999999",
    "lng": "135.9448086",
    "zoom": "20",
    "image": "https://japan-heritage.bunka.go.jp/ja/datas/cache/images/2022/08/15/500x343_2ae395417f98b42be3d881be00011165_95b2769fff42e0664b16b1cc463f9d9acca67ca9.jpeg"
  },
  {
    "pidx": "1324",
    "jhno": "32",
    "pno": "11",
    "url": "https://japan-heritage.bunka.go.jp/ja/culturalproperties/result/2185/",
    "status": "町史跡",
    "name": "鯨供養碑",
    "yomi": "",
    "spot": "和歌山県太地町",
    "lat": "33.59086916925959",
    "lng": "135.94482475903476",
    "zoom": "17",
    "image": "https://japan-heritage.bunka.go.jp/ja/datas/cache/images/2022/08/15/500x343_2ae395417f98b42be3d881be00011165_f1d12866fa31caedcd61004fdb20bf2da1c1fbd5.jpeg"
  },
  {
    "pidx": "1325",
    "jhno": "32",
    "pno": "12",
    "url": "https://japan-heritage.bunka.go.jp/ja/culturalproperties/result/2186/",
    "status": "町史跡",
    "name": "古式捕鯨 支度部屋跡",
    "yomi": "",
    "spot": "和歌山県太地町",
    "lat": "33.594560762712725",
    "lng": "135.9607438476272",
    "zoom": "19",
    "image": "https://japan-heritage.bunka.go.jp/ja/datas/cache/images/2022/08/15/500x343_2ae395417f98b42be3d881be00011165_4f0d7e272e73ff31467b7078b2fe3ca8d94ce23f.jpeg"
  },
  {
    "pidx": "1326",
    "jhno": "32",
    "pno": "13",
    "url": "https://japan-heritage.bunka.go.jp/ja/culturalproperties/result/2187/",
    "status": "町史跡",
    "name": "古式捕鯨 狼煙場跡",
    "yomi": "",
    "spot": "和歌山県太地町",
    "lat": "33.59531090953516",
    "lng": "135.96095305993038",
    "zoom": "19",
    "image": "https://japan-heritage.bunka.go.jp/ja/datas/cache/images/2022/08/15/500x343_2ae395417f98b42be3d881be00011165_cac758980b4bb06cd50ebfb3461d65e119b311c1.jpeg"
  },
  {
    "pidx": "1327",
    "jhno": "32",
    "pno": "14",
    "url": "https://japan-heritage.bunka.go.jp/ja/culturalproperties/result/2188/",
    "status": "未指定",
    "name": "燈明崎 燈明台跡",
    "yomi": "",
    "spot": "和歌山県太地町",
    "lat": "33.59531090953516",
    "lng": "135.96095305993038",
    "zoom": "19",
    "image": "https://japan-heritage.bunka.go.jp/ja/datas/cache/images/2022/08/15/500x343_2ae395417f98b42be3d881be00011165_929e6c4c3ebb8b096090818ded46117e778fa520.jpeg"
  },
  {
    "pidx": "1328",
    "jhno": "32",
    "pno": "15",
    "url": "https://japan-heritage.bunka.go.jp/ja/culturalproperties/result/2189/",
    "status": "未指定",
    "name": "燈明崎 山見台跡",
    "yomi": "",
    "spot": "和歌山県太地町",
    "lat": "33.59531090953516",
    "lng": "135.96095305993038",
    "zoom": "19",
    "image": "https://japan-heritage.bunka.go.jp/ja/datas/cache/images/2022/08/15/500x343_2ae395417f98b42be3d881be00011165_95f130adb6bc7fceda04049c67c187079bf40590.jpeg"
  },
  {
    "pidx": "1329",
    "jhno": "32",
    "pno": "16",
    "url": "https://japan-heritage.bunka.go.jp/ja/culturalproperties/result/2190/",
    "status": "町史跡",
    "name": "古式捕鯨 高塚連絡所跡",
    "yomi": "",
    "spot": "和歌山県太地町",
    "lat": "33.58773493016919",
    "lng": "135.95054072505025",
    "zoom": "19",
    "image": "https://japan-heritage.bunka.go.jp/ja/datas/cache/images/2022/08/15/500x343_2ae395417f98b42be3d881be00011165_5c9f46fd6cefa44b1d9fd487a9182ad9e8698ffd.jpeg"
  },
  {
    "pidx": "1330",
    "jhno": "32",
    "pno": "17",
    "url": "https://japan-heritage.bunka.go.jp/ja/culturalproperties/result/2191/",
    "status": "未指定",
    "name": "和田の岩門",
    "yomi": "",
    "spot": "和歌山県太地町",
    "lat": "33.589899274775775",
    "lng": "135.94735492317523",
    "zoom": "20",
    "image": "https://japan-heritage.bunka.go.jp/ja/datas/cache/images/2022/08/15/500x343_2ae395417f98b42be3d881be00011165_8e3ed3f9d67638e0679c4dd5aa811787f3886f29.jpeg"
  },
  {
    "pidx": "1331",
    "jhno": "32",
    "pno": "18",
    "url": "https://japan-heritage.bunka.go.jp/ja/culturalproperties/result/5739/",
    "status": "未指定",
    "name": "太地角右衛門の墓",
    "yomi": "",
    "spot": "和歌山県太地町",
    "lat": "33.591490799999995",
    "lng": "135.9440291",
    "zoom": "16",
    "image": "https://japan-heritage.bunka.go.jp/ja/datas/cache/images/2022/09/09/500x343_2ae395417f98b42be3d881be00011165_5a356757d1872deed982ca07a4a90fd1251cb7b9.jpg"
  },
  {
    "pidx": "1332",
    "jhno": "32",
    "pno": "19",
    "url": "https://japan-heritage.bunka.go.jp/ja/culturalproperties/result/5741/",
    "status": "未指定",
    "name": "刺し加子墓",
    "yomi": "",
    "spot": "和歌山県太地町",
    "lat": "33.58825070000004",
    "lng": "135.94691570000003",
    "zoom": "17",
    "image": "https://japan-heritage.bunka.go.jp/ja/datas/cache/images/2022/09/09/500x343_2ae395417f98b42be3d881be00011165_436c83925802984e6089acf9ac77f27525d5f6ec.jpg"
  },
  {
    "pidx": "1333",
    "jhno": "32",
    "pno": "20",
    "url": "https://japan-heritage.bunka.go.jp/ja/culturalproperties/result/5743/",
    "status": "未指定",
    "name": "梶取崎　狼煙場跡",
    "yomi": "",
    "spot": "和歌山県太地町",
    "lat": "33.58227860000006",
    "lng": "135.9593825",
    "zoom": "17",
    "image": "https://japan-heritage.bunka.go.jp/ja/datas/cache/images/2022/09/09/500x343_2ae395417f98b42be3d881be00011165_63acf3a2488c41b54b0e193baca95084f4ae8354.jpg"
  },
  {
    "pidx": "1334",
    "jhno": "32",
    "pno": "21",
    "url": "https://japan-heritage.bunka.go.jp/ja/culturalproperties/result/2192/",
    "status": "県無形民俗",
    "name": "三輪崎の鯨踊",
    "yomi": "",
    "spot": "和歌山県新宮市",
    "lat": "33.683544109573944",
    "lng": "135.98316268873805",
    "zoom": "17",
    "image": "https://japan-heritage.bunka.go.jp/ja/datas/cache/images/2022/08/15/500x343_2ae395417f98b42be3d881be00011165_c7e211127a0826eb6831f97071fd0bd8c2fb82af.jpeg"
  },
  {
    "pidx": "1335",
    "jhno": "32",
    "pno": "22",
    "url": "https://japan-heritage.bunka.go.jp/ja/culturalproperties/result/2193/",
    "status": "未指定",
    "name": "羽指中建立の石祠",
    "yomi": "",
    "spot": "和歌山県新宮市",
    "lat": "33.69586050000002",
    "lng": "135.9889197",
    "zoom": "18",
    "image": "https://japan-heritage.bunka.go.jp/ja/datas/cache/images/2022/08/15/500x343_2ae395417f98b42be3d881be00011165_b8e51d3d8ce2cd76aa448b26de1000bce8eaf75a.jpeg"
  },
  {
    "pidx": "1336",
    "jhno": "32",
    "pno": "23",
    "url": "https://japan-heritage.bunka.go.jp/ja/culturalproperties/result/2194/",
    "status": "未指定",
    "name": "鯨山見跡",
    "yomi": "",
    "spot": "和歌山県新宮市",
    "lat": "33.69585150000001",
    "lng": "135.99259970000003",
    "zoom": "18",
    "image": "https://japan-heritage.bunka.go.jp/ja/datas/cache/images/2022/09/09/500x343_2ae395417f98b42be3d881be00011165_5d70711ad9179c7279e082bb3f09f04d3b5c037d.jpg"
  },
  {
    "pidx": "1337",
    "jhno": "32",
    "pno": "24",
    "url": "https://japan-heritage.bunka.go.jp/ja/culturalproperties/result/5747/",
    "status": "未指定",
    "name": "孔島厳島神社の石造物",
    "yomi": "",
    "spot": "和歌山県新宮市",
    "lat": "33.6811666666667",
    "lng": "135.98913888888887",
    "zoom": "17",
    "image": "https://japan-heritage.bunka.go.jp/ja/datas/cache/images/2022/09/09/500x343_2ae395417f98b42be3d881be00011165_60599f151accb524ed6deefefbffe6e53ecf9837.jpg"
  },
  {
    "pidx": "1338",
    "jhno": "32",
    "pno": "25",
    "url": "https://japan-heritage.bunka.go.jp/ja/culturalproperties/result/5749/",
    "status": "未指定",
    "name": "三輪崎八幡神社の石灯籠",
    "yomi": "",
    "spot": "和歌山県新宮市",
    "lat": "33.68913888888889",
    "lng": "135.98288888888888",
    "zoom": "17",
    "image": "https://japan-heritage.bunka.go.jp/ja/datas/cache/images/2022/09/09/500x343_2ae395417f98b42be3d881be00011165_76e6732a3d3833794b641b8e7739287c570d160a.jpg"
  },
  {
    "pidx": "1339",
    "jhno": "32",
    "pno": "26",
    "url": "https://japan-heritage.bunka.go.jp/ja/culturalproperties/result/2195/",
    "status": "未指定",
    "name": "青岸渡寺の魚霊供養碑",
    "yomi": "",
    "spot": "和歌山県那智勝浦町",
    "lat": "33.6691474",
    "lng": "135.88984870000002",
    "zoom": "18",
    "image": "https://japan-heritage.bunka.go.jp/ja/datas/cache/images/2022/08/15/500x343_2ae395417f98b42be3d881be00011165_7a27c871aa695230b6716066d0374691c5c91fa1.jpeg"
  },
  {
    "pidx": "1340",
    "jhno": "32",
    "pno": "27",
    "url": "https://japan-heritage.bunka.go.jp/ja/culturalproperties/result/2196/",
    "status": "未指定",
    "name": "鹽竃神社のせみ祭り",
    "yomi": "",
    "spot": "和歌山県那智勝浦町",
    "lat": "33.561054200000015",
    "lng": "135.89508520000004",
    "zoom": "18",
    "image": "https://japan-heritage.bunka.go.jp/ja/datas/cache/images/2022/08/15/500x343_2ae395417f98b42be3d881be00011165_0f2e6395567df1e714e9150f81d60634b19e9a24.jpeg"
  },
  {
    "pidx": "1341",
    "jhno": "32",
    "pno": "28",
    "url": "https://japan-heritage.bunka.go.jp/ja/culturalproperties/result/2197/",
    "status": "未指定",
    "name": "浜の宮のお弓祭り",
    "yomi": "",
    "spot": "和歌山県那智勝浦町",
    "lat": "33.64488320000001",
    "lng": "135.93456949999995",
    "zoom": "18",
    "image": "https://japan-heritage.bunka.go.jp/ja/datas/cache/images/2022/08/15/500x343_2ae395417f98b42be3d881be00011165_67561b07b35a5b4f4c1efbd532bb53480059d4a2.jpeg"
  },
  {
    "pidx": "1342",
    "jhno": "32",
    "pno": "29",
    "url": "https://japan-heritage.bunka.go.jp/ja/culturalproperties/result/5753/",
    "status": "未指定",
    "name": "宇久井半島の山見台跡群",
    "yomi": "",
    "spot": "和歌山県那智勝浦町",
    "lat": "33.64932559999998",
    "lng": "135.9794607",
    "zoom": "17",
    "image": "https://japan-heritage.bunka.go.jp/ja/datas/cache/images/2022/09/09/500x343_2ae395417f98b42be3d881be00011165_84c54c195850e69d47712d330617625d4d9b7234.jpg"
  }
]